sentinel/__init__.py
sentinel/entrypoint.py
natera_add_sentinel-1.0.0.dist-info/LICENSE.txt
natera_add_sentinel-1.0.0.dist-info/METADATA
natera_add_sentinel-1.0.0.dist-info/WHEEL
natera_add_sentinel-1.0.0.dist-info/entry_points.txt
natera_add_sentinel-1.0.0.dist-info/top_level.txt
natera_add_sentinel-1.0.0.dist-info/RECORD
